MANIFEST.in
README.rst
setup.py
conversejs/__init__.py
conversejs/admin.py
conversejs/boshclient.py
conversejs/conf.py
conversejs/forms.py
conversejs/models.py
conversejs/tests.py
conversejs/utils.py
conversejs/views.py
conversejs/xmpp.py
conversejs/migrations/0001_initial.py
conversejs/migrations/__init__.py
conversejs/static/converse.js/converse.min.css
conversejs/static/converse.js/converse.min.js
conversejs/static/converse.js/fonticons/Read Me.txt
conversejs/static/converse.js/fonticons/index.html
conversejs/static/converse.js/fonticons/license.txt
conversejs/static/converse.js/fonticons/lte-ie7.js
conversejs/static/converse.js/fonticons/style.css
conversejs/static/converse.js/fonticons/fonts/Converse-js.dev.svg
conversejs/static/converse.js/fonticons/fonts/Converse-js.eot
conversejs/static/converse.js/fonticons/fonts/Converse-js.svg
conversejs/static/converse.js/fonticons/fonts/Converse-js.ttf
conversejs/static/converse.js/fonticons/fonts/Converse-js.woff
conversejs/static/converse.js/images/bg.png
conversejs/static/converse.js/images/bg_hr.png
conversejs/static/converse.js/images/blacktocat.png
conversejs/static/converse.js/images/icon_download.png
conversejs/static/converse.js/images/spinner.gif
conversejs/static/converse.js/images/sprite_download.png
conversejs/templates/conversejs/includes/base.html
conversejs/templates/conversejs/includes/chatpanel.html
conversejs/templates/conversejs/includes/initialize.html
conversejs/templates/conversejs/includes/static.html
conversejs/templatetags/__init__.py
conversejs/templatetags/conversejs.py
django_conversejs.egg-info/PKG-INFO
django_conversejs.egg-info/SOURCES.txt
django_conversejs.egg-info/dependency_links.txt
django_conversejs.egg-info/requires.txt
django_conversejs.egg-info/top_level.txt