Metadata-Version: 1.0
Name: django-conversejs
Version: 0.2.9
Summary: Adds converse.js (javascript XMPP client) to Django
Home-page: https://github.com/TracyWebTech/django-conversejs
Author: Sergio Oliveira
Author-email: sergio@tracy.com.br
License: MPL v2.0
Platform: UNKNOWN
Classifier: Development Status :: 4 - Beta
Classifier: Environment :: Web Environment
Classifier: Framework :: Django
Classifier: Intended Audience :: Developers
Classifier: License :: OSI Approved :: Mozilla Public License 2.0 (MPL 2.0)
Classifier: Operating System :: OS Independent
Classifier: Programming Language :: Python
Classifier: Programming Language :: Python :: 2.6
Classifier: Programming Language :: Python :: 2.7
